pdns_exporter/__init__.py
pdns_exporter/exporter.py
pdns_exporter/settings.conf
pdns_exporter/webapp.py
pdns_exporter-0.3.0.dist-info/LICENSE
pdns_exporter-0.3.0.dist-info/METADATA
pdns_exporter-0.3.0.dist-info/WHEEL
pdns_exporter-0.3.0.dist-info/entry_points.txt
pdns_exporter-0.3.0.dist-info/top_level.txt
pdns_exporter-0.3.0.dist-info/RECORD
