Metadata-Version: 2.1
Name: pdns-exporter
Version: 0.3.0
Summary: PowerDNS records exporter
Home-page: https://github.com/dmachard/python-pdns-exporter
Author: Denis MACHARD
Author-email: d.machard@gmail.com
Keywords: powerdns pdns database exporter mysql zone bind
Platform: any
Classifier: License :: OSI Approved :: MIT License
Classifier: Programming Language :: Python :: 3
Classifier: Operating System :: OS Independent
Classifier: Topic :: Software Development :: Libraries
License-File: LICENSE
Requires-Dist: SQLAlchemy
Requires-Dist: aiohttp
Requires-Dist: aiomysql
Requires-Dist: requests
